pywebpack/__init__.py
pywebpack/bundle.py
pywebpack/errors.py
pywebpack/helpers.py
pywebpack/manifests.py
pywebpack/project.py
pywebpack/storage.py
pywebpack-2.2.1.dist-info/licenses/AUTHORS.rst
pywebpack-2.2.1.dist-info/licenses/LICENSE
pywebpack-2.2.1.dist-info/METADATA
pywebpack-2.2.1.dist-info/WHEEL
pywebpack-2.2.1.dist-info/top_level.txt
pywebpack-2.2.1.dist-info/RECORD
