Metadata-Version: 2.4
Name: pywebpack
Version: 2.2.1
Summary: Webpack integration layer for Python.
Home-page: https://github.com/inveniosoftware/pywebpack
Author: CERN
Author-email: info@inveniosoftware.org
License: BSD
Keywords: webpack npm node
Platform: any
Classifier: Development Status :: 5 - Production/Stable
Requires-Python: >=3.7
License-File: LICENSE
License-File: AUTHORS.rst
Requires-Dist: pynpm>=0.1.0
Provides-Extra: tests
Requires-Dist: pytest-black>=0.3.0; extra == "tests"
Requires-Dist: pytest-cache>=1.0; extra == "tests"
Requires-Dist: pytest-invenio<3.0.0,>=2.1.0; extra == "tests"
Requires-Dist: sphinx>=4.5; extra == "tests"
Provides-Extra: docs
Dynamic: license-file
